{
    "Uber": {
        "cost": 12.148835629715446,
        "env_tax": 0.020000000000000004,
        "route": "(87,92), (87,93), (87,94), (88,94)",
        "time": 7.416950970058834
    },
    "Uber_Train_Uber": {
        "cost": 25.556574547298734,
        "env_tax": 0.065,
        "route": "(87,92), (88,92), (89,92), (89,91), (90,91), (90,90)|(90,90), (90,90)|(90,90), (90,91), (89,91), (89,92), (88,92), (88,93), (88,94)",
        "time": 23.630360217449237
    },
    "Uber_Train_Walk": {
        "cost": 12.77079105866302,
        "env_tax": 0.030000000000000006,
        "route": "(87,92), (88,92), (89,92), (89,91), (90,91), (90,90)|(90,90), (90,90)|(90,90), (89,90), (88,90), (88,90), (88,91), (88,92), (88,93), (88,94)",
        "time": 460.2323464432792
    },
    "Walk": {
        "cost": 0,
        "env_tax": 0,
        "route": "(87,92), (88,92), (88,92), (88,93), (88,94)",
        "time": 223.6936292054402
    },
    "Walk_Train_Uber": {
        "cost": 12.90092199292,
        "env_tax": 0.035,
        "route": "(87,92), (88,92), (89,92), (90,92), (90,92), (90,91), (90,90)|(90,90), (90,90)|(90,90), (90,91), (89,91), (89,92), (88,92), (88,93), (88,94)",
        "time": 389.81155645021744
    },
    "Walk_Train_Walk": {
        "cost": 0.2,
        "env_tax": 0,
        "route": "(87,92), (88,92), (89,92), (90,92), (90,92), (90,91), (90,90)|(90,90), (90,90)|(90,90), (89,90), (88,90), (88,90), (88,91), (88,92), (88,93), (88,94)",
        "time": 828.0676436598436
    }
}